fuzzypanda/__init__.py
fuzzypanda/matching.py
fuzzypanda/preprocess.py
fuzzypanda-0.1.1.dist-info/LICENSE.txt
fuzzypanda-0.1.1.dist-info/METADATA
fuzzypanda-0.1.1.dist-info/WHEEL
fuzzypanda-0.1.1.dist-info/top_level.txt
fuzzypanda-0.1.1.dist-info/RECORD
