Metadata-Version: 2.1
Name: fuzzypanda
Version: 0.1.1
Summary: Toolkit for performing fuzzy joins with Symspell framework
Home-page: https://github.com/cody-joe-gilbert/fuzzypanda
Author: Cody Joe Gilbert
Author-email: cody@codyjoe.com
License: MIT
Keywords: fuzzy join pandas Symspell
Platform: UNKNOWN
Classifier: Development Status :: 4 - Beta
Classifier: License :: OSI Approved :: MIT License
Classifier: Programming Language :: Python :: 3.6
Classifier: Operating System :: OS Independent
Classifier: Topic :: Scientific/Engineering :: Information Analysis
Requires-Python: >=3
Requires-Dist: symspellpy
